iheart/__init__.py
iheart/__main__.py
iheart/colors.py
iheart/conf.py
iheart/player.py
iheart/storage.py
iheart/stations/__init__.py
iheart/stations/base.py
iheart/stations/playlist.py
iheart/stations/aNON_radio/__init__.py
iheart/stations/aNON_radio/stations.py
iheart/stations/iheart_radio/__init__.py
iheart/stations/iheart_radio/client.py
iheart/stations/iheart_radio/stations.py
iheart/stations/internet_radio/__init__.py
iheart/stations/internet_radio/client.py
iheart/stations/internet_radio/stations.py
iheart_cli-0.7.3.dist-info/LICENSE
iheart_cli-0.7.3.dist-info/METADATA
iheart_cli-0.7.3.dist-info/WHEEL
iheart_cli-0.7.3.dist-info/entry_points.txt
iheart_cli-0.7.3.dist-info/top_level.txt
iheart_cli-0.7.3.dist-info/RECORD
