Metadata-Version: 2.1
Name: iheart-cli
Version: 0.7.3
Summary: Command line utility to search and play iHeartRadio
Home-page: https://github.com/shashfrankenstien/iheart-cli
Author: Shashank Gopikrishna
Author-email: shashank.gopikrishna@gmail.com
License: MIT
License-File: LICENSE
Requires-Dist: python-vlc >=3.0.12118
Requires-Dist: requests >=2.23.0
Requires-Dist: beautifulsoup4 >=4.11.1
Requires-Dist: lxml >=4.8.0
